puwr.py
py_uwerr-0.1.dist-info/LICENSE
py_uwerr-0.1.dist-info/WHEEL
py_uwerr-0.1.dist-info/METADATA
py_uwerr-0.1.dist-info/RECORD
