Metadata-Version: 2.1
Name: py-uwerr
Version: 0.1
Summary: Pure Python library that implements Wolff's method to compute autocorrelation timesof Monte Carlo series.
Keywords: Monte Carlo,autocorrelation time,tau int,statistics
Author-email: Dirk Hesse <herr.dirk.hesse@gmail.com>
Requires-Python: >=3.6
Classifier: Development Status :: 4 - Beta
Classifier: Intended Audience :: Science/Research
Classifier: License :: OSI Approved :: MIT License
Classifier: Operating System :: OS Independent
Classifier: Programming Language :: Python
Classifier: Programming Language :: Python :: 3
Classifier: Programming Language :: Python :: 3.6
Classifier: Programming Language :: Python :: 3.7
Classifier: Programming Language :: Python :: 3.8
Classifier: Programming Language :: Python :: 3.9
Classifier: Topic :: Scientific/Engineering
Classifier: Topic :: Software Development :: Libraries
Requires-Dist: numpy
Requires-Dist: scipy
Requires-Dist: matplotlib
Requires-Dist: tox==3.24.1 ; extra == "test"
Project-URL: github, https://github.com/dhesse/py-uwerr
Provides-Extra: test
